README.md
func_adl_xAOD/__init__.py
func_adl_xAOD/version.txt
func_adl_xAOD/atlas/xaod/__init__.py
func_adl_xAOD/atlas/xaod/event_collections.py
func_adl_xAOD/atlas/xaod/executor.py
func_adl_xAOD/atlas/xaod/jets.py
func_adl_xAOD/atlas/xaod/local_dataset.py
func_adl_xAOD/atlas/xaod/query_ast_visitor.py
func_adl_xAOD/cms/aod/__init__.py
func_adl_xAOD/cms/aod/cms_functions.py
func_adl_xAOD/cms/aod/event_collections.py
func_adl_xAOD/cms/aod/executor.py
func_adl_xAOD/cms/aod/local_dataset.py
func_adl_xAOD/cms/aod/query_ast_visitor.py
func_adl_xAOD/cms/miniaod/__init__.py
func_adl_xAOD/cms/miniaod/cms_functions.py
func_adl_xAOD/cms/miniaod/event_collections.py
func_adl_xAOD/cms/miniaod/executor.py
func_adl_xAOD/cms/miniaod/local_dataset.py
func_adl_xAOD/cms/miniaod/query_ast_visitor.py
func_adl_xAOD/common/__init__.py
func_adl_xAOD/common/ast_to_cpp_translator.py
func_adl_xAOD/common/cpp_ast.py
func_adl_xAOD/common/cpp_functions.py
func_adl_xAOD/common/cpp_representation.py
func_adl_xAOD/common/cpp_types.py
func_adl_xAOD/common/cpp_vars.py
func_adl_xAOD/common/event_collections.py
func_adl_xAOD/common/executor.py
func_adl_xAOD/common/generated_code.py
func_adl_xAOD/common/local_dataset.py
func_adl_xAOD/common/math_utils.py
func_adl_xAOD/common/meta_data.py
func_adl_xAOD/common/result_ttree.py
func_adl_xAOD/common/statement.py
func_adl_xAOD/common/util_scope.py
func_adl_xAOD/common/utils.py
func_adl_xAOD/template/atlas/r21/ATestRun_eljob.py
func_adl_xAOD/template/atlas/r21/README.md
func_adl_xAOD/template/atlas/r21/package_CMakeLists.txt
func_adl_xAOD/template/atlas/r21/query.cxx
func_adl_xAOD/template/atlas/r21/query.h
func_adl_xAOD/template/atlas/r21/runner.sh
func_adl_xAOD/template/cms/r5/Analyzer.cc
func_adl_xAOD/template/cms/r5/BuildFile.xml
func_adl_xAOD/template/cms/r5/README.md
func_adl_xAOD/template/cms/r5/analyzer_cfg.py
func_adl_xAOD/template/cms/r5/copy_root_tree.C
func_adl_xAOD/template/cms/r5/runner.sh
func_adl_xAOD/template/cms/r7/Analyzer.cc
func_adl_xaod-2.2.4.dist-info/METADATA
func_adl_xaod-2.2.4.dist-info/WHEEL
func_adl_xaod-2.2.4.dist-info/RECORD
