Metadata-Version: 2.4
Name: func_adl_xAOD
Version: 2.2.4
Summary: Functional Analysis Description Language backend for accessing ATLAS xAOD files.
Author-email: "G. Watts (IRIS-HEP/UW Seattle)" <gwatts@uw.edu>
Maintainer-email: "Gordon Watts (IRIS-HEP/UW Seattle)" <gwatts@uw.edu>
License: MIT
Classifier: Development Status :: 5 - Production/Stable
Classifier: Intended Audience :: Developers
Classifier: Intended Audience :: Information Technology
Classifier: Programming Language :: Python
Classifier: Programming Language :: Python :: 3.9
Classifier: Programming Language :: Python :: 3.10
Classifier: Programming Language :: Python :: 3.11
Classifier: Programming Language :: Python :: 3.12
Classifier: Programming Language :: Python :: 3.13
Classifier: Topic :: Software Development
Classifier: Topic :: Utilities
Requires-Python: >=3.9
Requires-Dist: func-adl>3.4
Requires-Dist: jinja2
Requires-Dist: qastle
Requires-Dist: requests
Requires-Dist: retry
Provides-Extra: local
Requires-Dist: python-on-whales; extra == 'local'
Provides-Extra: test
Requires-Dist: asyncmock; extra == 'test'
Requires-Dist: autopep8; extra == 'test'
Requires-Dist: awkward; extra == 'test'
Requires-Dist: black; extra == 'test'
Requires-Dist: coverage; extra == 'test'
Requires-Dist: flake8; extra == 'test'
Requires-Dist: pandas; extra == 'test'
Requires-Dist: pytest-asyncio; extra == 'test'
Requires-Dist: pytest-cov; extra == 'test'
Requires-Dist: pytest-mock; extra == 'test'
Requires-Dist: pytest>=3.9; extra == 'test'
Requires-Dist: testfixtures; extra == 'test'
Requires-Dist: twine; extra == 'test'
Requires-Dist: uproot; extra == 'test'
Requires-Dist: wheel; extra == 'test'
